telegram_notifier_bot/__init__.py
telegram_notifier_bot-1.0.0.dist-info/LICENSE
telegram_notifier_bot-1.0.0.dist-info/METADATA
telegram_notifier_bot-1.0.0.dist-info/WHEEL
telegram_notifier_bot-1.0.0.dist-info/top_level.txt
telegram_notifier_bot-1.0.0.dist-info/RECORD
