Metadata-Version: 2.1
Name: telegram-notifier-bot
Version: 1.0.0
Summary: Send a notification to a Telegram user or group.
Author-email: p4irin <139928764+p4irin@users.noreply.github.com>
Project-URL: Homepage, https://github.com/p4irin/telegram_notifier_bot
Project-URL: Bug Tracker, https://github.com/p4irin/telegram_notifier_bot/issues
Keywords: telegram,bot
Classifier: Programming Language :: Python :: 3
Classifier: Programming Language :: Python :: 3.8
Classifier: Operating System :: POSIX :: Linux
Classifier: Intended Audience :: Developers
Classifier: Topic :: Software Development :: Libraries :: Python Modules
Classifier: License :: OSI Approved :: MIT License
Requires-Python: >=3.8.10
License-File: LICENSE
Requires-Dist: requests >=2.31.0
Provides-Extra: dev
Requires-Dist: build ==0.10.0 ; extra == 'dev'
Requires-Dist: twine >=4.0.2 ; extra == 'dev'
Requires-Dist: bumpver >=2023.1126 ; extra == 'dev'
Provides-Extra: test
Requires-Dist: python-dotenv[cli] >=1.0.0 ; extra == 'test'
